<?xml version="1.0"?>
<!--
/**
 * Created By : Rohan Hapani
 */
-->
<config xmlns:xsi="http://www.w3.org/2001/XMLSchema-instance" xsi:noNamespaceSchemaLocation="urn:magento:framework:Api/etc/extension_attributes.xsd">
    <extension_attributes for="Magento\SalesRule\Api\Data\RuleInterface">
        <attribute code="image" type="Wiki\StoreApi\Api\Data\RuleInterface[]"/>
    </extension_attributes>
    <extension_attributes for="Magento\Customer\Api\Data\AddressInterface">
        <attribute code="district" type="string"/>
        <attribute code="sub_district" type="string"/>
    </extension_attributes>
    <extension_attributes for="Magento\Customer\Api\Data\CustomerInterface">
        <attribute code="card_info" type="Wiki\StoreApi\Api\Data\CardInterface[]"/>
        <attribute code="settings" type="Wiki\StoreApi\Api\Data\SettingInterface[]"/>
    </extension_attributes>
    <extension_attributes for="Magento\Sales\Api\Data\OrderInterface">
        <attribute code="shipping_address" type="Wiki\StoreApi\Api\Data\AddressInterface" />
        <attribute code="billing_address" type="Wiki\StoreApi\Api\Data\AddressInterface" />
    </extension_attributes>
</config>

